setup.py
pyforecastapp/__init__.py
pyforecastapp.egg-info/PKG-INFO
pyforecastapp.egg-info/SOURCES.txt
pyforecastapp.egg-info/dependency_links.txt
pyforecastapp.egg-info/requires.txt
pyforecastapp.egg-info/top_level.txt