Metadata-Version: 1.0
Name: pyforecastapp
Version: 1.0.2
Summary: Python API for ForecastApp.com
Home-page: http://github.com/project-ada/pyforecastapp
Author: Miiro Juuso
Author-email: miiro.juuso@artirix.com
License: BSD
Keywords: forecast api
Platform: UNKNOWN
